[ 
  {
  "name": "031_Ayikz",
  "app_id": "6755466094",
  "store_url": "https://apps.apple.com/us/app/id6755466094",
  "listed_at": "2025-11-25"
  },
  {
    "name": "032_Fzitay",
    "app_id": "6755903551",
    "store_url": "https://apps.apple.com/us/app/id6755903551",
    "listed_at": "2025-12-02"
  },
  {
    "name": "033_Koizya",
    "app_id": "6756290698",
    "store_url": "https://apps.apple.com/us/app/id6756290698",
    "listed_at": "2025-12-11"
  },
  {
    "name": "036_Baxoya",
    "app_id": "6756337396",
    "store_url": "https://apps.apple.com/us/app/id6756337396",
    "listed_at": "2025-12-13"
  },
  {
    "name": "037_Mozyor",
    "app_id": "6756509310",
    "store_url": "https://apps.apple.com/ph/app/id6756509310",
    "listed_at": "2025-12-17"
  },
  {
    "name": "038_Yoripo",
    "app_id": "6756511774",
    "store_url": "https://apps.apple.com/ph/app/id6756511774",
    "listed_at": "2025-12-22"
  },
  {
    "name": "039_Letoso",
    "app_id": "6756777684",
    "store_url": "https://apps.apple.com/us/app/id6756777684",
    "listed_at": "2025-12-24"
  },
  {
    "name": "040_Terpoy",
    "app_id": "6756807858",
    "store_url": "https://apps.apple.com/us/app/id6756807858",
    "listed_at": "2026-01-05"
  },
  {
    "name": "0678_Test",
    "app_id": "678901231",
    "store_url": "https://apps.apple.com/us/app/id678901231",
    "listed_at": "2026-01-05"
  }
]


